oxygen/__init__.py
oxygen/__main__.py
oxygen/base_handler.py
oxygen/config.py
oxygen/config.yml
oxygen/config_original.yml
oxygen/errors.py
oxygen/gatling.py
oxygen/junit.py
oxygen/oxygen.py
oxygen/oxygen_handler_result.py
oxygen/robot3_interface.py
oxygen/robot4_interface.py
oxygen/robot_interface.py
oxygen/utils.py
oxygen/version.py
oxygen/zap.py
robotframework_oxygen-0.3.dist-info/LICENSE
robotframework_oxygen-0.3.dist-info/METADATA
robotframework_oxygen-0.3.dist-info/WHEEL
robotframework_oxygen-0.3.dist-info/top_level.txt
robotframework_oxygen-0.3.dist-info/RECORD
