Metadata-Version: 2.1
Name: robotframework-oxygen
Version: 0.3
Summary: Oxygen is an extensible tool for Robot Framework that enables you to integrate running other testing tools and their reports as part of Robot Framework's reporting.
Home-page: 
Author: Eficode Oy
Author-email: info@eficode.com
License: MIT
Keywords: robotframework testing testautomation acceptancetesting atdd bddreporting testreporting
Classifier: Development Status :: 5 - Production/Stable
Classifier: Programming Language :: Python :: 3 :: Only
Classifier: Operating System :: OS Independent
Classifier: Topic :: Software Development :: Testing
Classifier: License :: OSI Approved :: MIT License
License-File: LICENSE
Requires-Dist: robotframework >=3.0.4
Requires-Dist: junitparser ==2.0
Requires-Dist: PyYAML >=3.13
Requires-Dist: pydantic >=2.4.2
